README.md
setup.cfg
setup.py
density_prob/Binomialdistribution.py
density_prob/Gaussiandistribution.py
density_prob/Generaldistribution.py
density_prob/__init__.py
density_prob.egg-info/PKG-INFO
density_prob.egg-info/SOURCES.txt
density_prob.egg-info/dependency_links.txt
density_prob.egg-info/not-zip-safe
density_prob.egg-info/top_level.txt