Metadata-Version: 1.0
Name: density-prob
Version: 0.1
Summary: Gaussian distributions
Home-page: UNKNOWN
Author: Adrian Brown
Author-email: UNKNOWN
License: UNKNOWN
Platform: UNKNOWN
